CirclesBertPython/__init__.py
CirclesBertPython/bert.py
CirclesBertPython/test_bert.py
local_bert_python_backend-0.0.15.dist-info/METADATA
local_bert_python_backend-0.0.15.dist-info/WHEEL
local_bert_python_backend-0.0.15.dist-info/top_level.txt
local_bert_python_backend-0.0.15.dist-info/RECORD
