Metadata-Version: 2.1
Name: local-bert-python-backend
Version: 0.0.15
Summary: PyPI Package for Circles Local Bert Python
Home-page: https://github.com/javatechy/dokr
Author: Circles
Author-email: info@bubbelz.life
Classifier: Programming Language :: Python :: 3
Classifier: License :: Other/Proprietary License
Classifier: Operating System :: OS Independent
